Metadata-Version: 2.1
Name: switch-mexico
Version: 2.0.8b3
Summary: SWITCH Power System Planning Model
Home-page: http://switch-model.org
Maintainer: Switch Authors
Maintainer-email: authors@switch-model.org
License: Apache v2
Keywords: renewable,power,energy,electricity,production cost,capacity expansion,planning,optimization
Platform: any
Classifier: Development Status :: 4 - Beta
Classifier: Environment :: Console
Classifier: Intended Audience :: Education
Classifier: Intended Audience :: End Users/Desktop
Classifier: Intended Audience :: Science/Research
Classifier: License :: OSI Approved :: Apache Software License
Classifier: Natural Language :: English
Classifier: Operating System :: Microsoft :: Windows
Classifier: Operating System :: MacOS :: MacOS X
Classifier: Operating System :: Unix
Classifier: Programming Language :: Python
Classifier: Programming Language :: Unix Shell
Classifier: Topic :: Scientific/Engineering
Classifier: Topic :: Software Development :: Libraries :: Python Modules
Provides-Extra: plotting
Provides-Extra: advanced
Provides-Extra: database_access
Requires-Dist: Pyomo (>=4.4.1)
Requires-Dist: testfixtures
Requires-Dist: pandas
Provides-Extra: advanced
Requires-Dist: numpy; extra == 'advanced'
Requires-Dist: scipy; extra == 'advanced'
Requires-Dist: rpy2; extra == 'advanced'
Requires-Dist: sympy; extra == 'advanced'
Provides-Extra: database_access
Requires-Dist: psycopg2; extra == 'database_access'
Provides-Extra: plotting
Requires-Dist: ggplot; extra == 'plotting'
